fullstop/__init__.py
fullstop/__main__.py
fullstop/api.py
fullstop/cli.py
fullstop/time.py
stups_fullstop-1.1.31.dist-info/DESCRIPTION.rst
stups_fullstop-1.1.31.dist-info/METADATA
stups_fullstop-1.1.31.dist-info/RECORD
stups_fullstop-1.1.31.dist-info/WHEEL
stups_fullstop-1.1.31.dist-info/entry_points.txt
stups_fullstop-1.1.31.dist-info/metadata.json
stups_fullstop-1.1.31.dist-info/top_level.txt
