Metadata-Version: 2.0
Name: stups-fullstop
Version: 1.1.31
Summary: Simple command line utility to view Fullstop violations
Home-page: https://github.com/zalando-stups/fullstop-cli
Author: Henning Jacobs
Author-email: henning.jacobs@zalando.de
License: Apache License 2.0
Keywords: fullstop audit violations
Platform: UNKNOWN
Classifier: Development Status :: 4 - Beta
Classifier: Environment :: Console
Classifier: Intended Audience :: Developers
Classifier: Intended Audience :: System Administrators
Classifier: License :: OSI Approved :: Apache Software License
Classifier: Operating System :: POSIX :: Linux
Classifier: Programming Language :: Python
Classifier: Programming Language :: Python :: 3.4
Classifier: Programming Language :: Python :: Implementation :: CPython
Requires-Dist: clickclick (>=1.0)
Requires-Dist: requests
Requires-Dist: stups-cli-support
Requires-Dist: stups-zign (>=1.1.26)
